flytekitplugins_mmcloud-1.16.12-py3.14-nspkg.pth
flytekitplugins/mmcloud/__init__.py
flytekitplugins/mmcloud/connector.py
flytekitplugins/mmcloud/task.py
flytekitplugins/mmcloud/utils.py
flytekitplugins_mmcloud-1.16.12.dist-info/METADATA
flytekitplugins_mmcloud-1.16.12.dist-info/WHEEL
flytekitplugins_mmcloud-1.16.12.dist-info/entry_points.txt
flytekitplugins_mmcloud-1.16.12.dist-info/namespace_packages.txt
flytekitplugins_mmcloud-1.16.12.dist-info/top_level.txt
flytekitplugins_mmcloud-1.16.12.dist-info/RECORD
